logcat_monitor/__init__.py
logcat_monitor/logcat_monitor.py
logcat_monitor/statistics.py
logcat_monitor/threadpool.py
logcat_monitor-0.0.25.dist-info/LICENSE
logcat_monitor-0.0.25.dist-info/METADATA
logcat_monitor-0.0.25.dist-info/WHEEL
logcat_monitor-0.0.25.dist-info/top_level.txt
logcat_monitor-0.0.25.dist-info/RECORD
