Metadata-Version: 2.1
Name: logcat-monitor
Version: 0.0.25
Summary: A tool of logcat monitor
Home-page: https://gitee.com/gentliu/logcat_monitor
Author: Gent Liu
Author-email: 94026236@qq.com
Classifier: Programming Language :: Python :: 3
Classifier: License :: OSI Approved :: MIT License
Classifier: Operating System :: OS Independent
License-File: LICENSE
